{
  "id": "371b1de8-ea77-43db-a16b-fb525d05b110",
  "file_name": "I1.png",
  "upload_date": "2025-05-31T15:39:52.302030",
  "summary": "The CBC report shows mild anemia characterized by low hemoglobin, low PCV, microcytosis (low MCV), and increased RDW, suggesting a possible iron deficiency or related cause. There is also mild neutropenia with a relative lymphocytosis, which may indicate an ongoing immune response or infection. Other parameters including platelet count are within normal limits.\n\n---",
  "detailed_analysis": "TRANSCRIPTION:\n\nS47 - RADHA DIAGNOSTICS  \nG.T.ROAD, JHUNSI, AWAS VIKAS COLONY,  \nYOJNA-2, NR POLICE CHOWKI, ALLAHABAD, UP  \n\nName: Mr. NEERAJ OJHA  \nLab No.: 242862201  \nAge: 27 Years  \nGender: Male  \nA/c Status: P  \nRef By: Dr. V. K. PANDEY  \n\nCollected: 1/8/2017 8:21:00 AM  \nReceived: 1/8/2017 8:37:03 AM  \nReported: 1/8/2017 6:52:30 PM  \nReport Status: Final  \n\nTest Name | Results | Units | Bio. Ref. Interval  \n---|---|---|---  \nCOMPLETE BLOOD COUNT (CBC)  \nHemoglobin | 12.00 | g/dL | 13.00 - 17.00  \nPacked Cell Volume (PCV) | 37.70 | % | 40.00 - 50.00  \nRBC Count | 5.79 | mill/mm3 | 4.50 - 5.50  \nMCV | 65.00 | fL | 80.00 - 100.00  \nMCH | 20.70 | pg | 27.00 - 32.00  \nMCHC | 31.90 | g/dL | 32.00 - 35.00  \nRed Cell Distribution Width (RDW) | 15.90 | % | 11.50 - 14.50  \nTotal Leukocyte Count (TLC) | 4.20 | thou/mm3 | 4.00 - 10.00  \n\nDifferential Leukocyte Count (DLC)  \nSegmented Neutrophils | 39.60 | % | 40.00 - 80.00  \nLymphocytes | 50.30 | % | 20.00 - 40.00  \nMonocytes | 8.10 | % | 2.00 - 10.00  \nEosinophils | 1.40 | % | 1.00 - 6.00  \nBasophils | 0.60 | % | <2.00  \n\nAbsolute Leukocyte Count  \nNeutrophils | 1.66 | thou/mm3 | 2.00 - 7.00  \nLymphocytes | 2.11 | thou/mm3 | 1.00 - 3.00  \nMonocytes | 0.34 | thou/mm3 | 0.20 - 1.00  \nEosinophils | 0.06 | thou/mm3 | 0.02 - 0.50  \nBasophils | 0.03 | thou/mm3 | 0.01 - 0.10  \n\nPlatelet Count | 245.0 | thou/mm3 | 150.00 - 450.00  \n\n---\n\nIDENTIFIED_PARAMETERS:\n\n- Hemoglobin: 12.00 g/dL (13.00 - 17.00 g/dL) - Low  \n- Packed Cell Volume (PCV): 37.70 % (40.00 - 50.00 %) - Low  \n- RBC Count: 5.79 mill/mm3 (4.50 - 5.50 mill/mm3) - High  \n- MCV: 65.00 fL (80.00 - 100.00 fL) - Low  \n- MCH: 20.70 pg (27.00 - 32.00 pg) - Low  \n- MCHC: 31.90 g/dL (32.00 - 35.00 g/dL) - Slightly Low  \n- Red Cell Distribution Width (RDW): 15.90 % (11.50 - 14.50 %) - High  \n- Total Leukocyte Count (TLC): 4.20 thou/mm3 (4.00 - 10.00 thou/mm3) - Normal  \n\nDifferential Leukocyte Count (DLC):  \n- Segmented Neutrophils: 39.60 % (40.00 - 80.00 %) - Slightly Low  \n- Lymphocytes: 50.30 % (20.00 - 40.00 %) - High  \n- Monocytes: 8.10 % (2.00 - 10.00 %) - Normal  \n- Eosinophils: 1.40 % (1.00 - 6.00 %) - Normal  \n- Basophils: 0.60 % (<2.00 %) - Normal  \n\nAbsolute Leukocyte Count:  \n- Neutrophils: 1.66 thou/mm3 (2.00 - 7.00 thou/mm3) - Low  \n- Lymphocytes: 2.11 thou/mm3 (1.00 - 3.00 thou/mm3) - Normal  \n- Monocytes: 0.34 thou/mm3 (0.20 - 1.00 thou/mm3) - Normal  \n- Eosinophils: 0.06 thou/mm3 (0.02 - 0.50 thou/mm3) - Normal  \n- Basophils: 0.03 thou/mm3 (0.01 - 0.10 thou/mm3) - Normal  \n\n- Platelet Count: 245.0 thou/mm3 (150.00 - 450.00 thou/mm3) - Normal  \n\n---\n\nOBSERVED_ABNORMALITIES:\n\n- Hemoglobin is low at 12.00 g/dL, below the normal range of 13.00 - 17.00 g/dL, indicating mild anemia.  \n- Packed Cell Volume (PCV) is slightly low at 37.70%, suggesting reduced red blood cell volume.  \n- RBC Count is slightly elevated at 5.79 mill/mm3, above the upper limit of 5.50 mill/mm3.  \n- MCV (mean corpuscular volume) is significantly low at 65.00 fL, indicating microcytic red blood cells, often seen in iron deficiency anemia or thalassemia.  \n- MCH (mean corpuscular hemoglobin) is low at 20.70 pg, indicating less hemoglobin per red blood cell.  \n- MCHC (mean corpuscular hemoglobin concentration) is slightly low at 31.90 g/dL.  \n- RDW (red cell distribution width) is elevated at 15.90%, indicating variation in red blood cell size, which supports anisocytosis often seen in anemia.  \n- Segmented neutrophils percentage is slightly low at 39.60%, and absolute neutrophil count is low at 1.66 thou/mm3, which may suggest mild neutropenia or a shift in white cell distribution.  \n- Lymphocytes percentage is high at 50.30%, though absolute lymphocyte count is normal, which may indicate a reactive or viral process.  \n\n---\n\nGENERAL_SUMMARY:\n\nThe CBC report shows mild anemia characterized by low hemoglobin, low PCV, microcytosis (low MCV), and increased RDW, suggesting a possible iron deficiency or related cause. There is also mild neutropenia with a relative lymphocytosis, which may indicate an ongoing immune response or infection. Other parameters including platelet count are within normal limits.\n\n---\n\nGENERAL_RECOMMENDATIONS:\n\n- Further evaluation for anemia is recommended, including iron studies (serum ferritin, serum iron, TIBC) to confirm iron deficiency or other causes.  \n- Monitor white blood cell counts and consider clinical correlation for possible infections or immune conditions due to neutropenia and lymphocytosis.  \n- Follow-up CBC after treatment or clinical intervention to assess response and progression.",
  "structured_data": {
    "overall_status": "abnormal",
    "summary": "The CBC report shows mild anemia characterized by low hemoglobin, low PCV, microcytosis (low MCV), and increased RDW, suggesting a possible iron deficiency or related cause. There is also mild neutropenia with a relative lymphocytosis, which may indicate an ongoing immune response or infection. Other parameters including platelet count are within normal limits.\n\n---",
    "parameters": [
      {
        "name": "Hemoglobin",
        "value": "12.00 g/dL",
        "reference_range": "13.00 - 17.00 g/dL",
        "status": "abnormal",
        "significance": null
      },
      {
        "name": "Packed Cell Volume (PCV)",
        "value": "37.70 %",
        "reference_range": "40.00 - 50.00 %",
        "status": "abnormal",
        "significance": null
      },
      {
        "name": "RBC Count",
        "value": "5.79 mill/mm3",
        "reference_range": "4.50 - 5.50 mill/mm3",
        "status": "abnormal",
        "significance": null
      },
      {
        "name": "MCV",
        "value": "65.00 fL",
        "reference_range": "80.00 - 100.00 fL",
        "status": "abnormal",
        "significance": null
      },
      {
        "name": "MCH",
        "value": "20.70 pg",
        "reference_range": "27.00 - 32.00 pg",
        "status": "abnormal",
        "significance": null
      },
      {
        "name": "MCHC",
        "value": "31.90 g/dL",
        "reference_range": "32.00 - 35.00 g/dL",
        "status": "abnormal",
        "significance": null
      },
      {
        "name": "Red Cell Distribution Width (RDW)",
        "value": "15.90 %",
        "reference_range": "11.50 - 14.50 %",
        "status": "abnormal",
        "significance": null
      },
      {
        "name": "Total Leukocyte Count (TLC)",
        "value": "4.20 thou/mm3",
        "reference_range": "4.00 - 10.00 thou/mm3",
        "status": "normal",
        "significance": null
      },
      {
        "name": "Segmented Neutrophils",
        "value": "39.60 %",
        "reference_range": "40.00 - 80.00 %",
        "status": "abnormal",
        "significance": null
      },
      {
        "name": "Lymphocytes",
        "value": "50.30 %",
        "reference_range": "20.00 - 40.00 %",
        "status": "abnormal",
        "significance": null
      },
      {
        "name": "Monocytes",
        "value": "8.10 %",
        "reference_range": "2.00 - 10.00 %",
        "status": "normal",
        "significance": null
      },
      {
        "name": "Eosinophils",
        "value": "1.40 %",
        "reference_range": "1.00 - 6.00 %",
        "status": "normal",
        "significance": null
      },
      {
        "name": "Basophils",
        "value": "0.60 %",
        "reference_range": "<2.00 %",
        "status": "normal",
        "significance": null
      },
      {
        "name": "Neutrophils",
        "value": "1.66 thou/mm3",
        "reference_range": "2.00 - 7.00 thou/mm3",
        "status": "abnormal",
        "significance": null
      },
      {
        "name": "Lymphocytes",
        "value": "2.11 thou/mm3",
        "reference_range": "1.00 - 3.00 thou/mm3",
        "status": "normal",
        "significance": null
      },
      {
        "name": "Monocytes",
        "value": "0.34 thou/mm3",
        "reference_range": "0.20 - 1.00 thou/mm3",
        "status": "normal",
        "significance": null
      },
      {
        "name": "Eosinophils",
        "value": "0.06 thou/mm3",
        "reference_range": "0.02 - 0.50 thou/mm3",
        "status": "normal",
        "significance": null
      },
      {
        "name": "Basophils",
        "value": "0.03 thou/mm3",
        "reference_range": "0.01 - 0.10 thou/mm3",
        "status": "normal",
        "significance": null
      },
      {
        "name": "Platelet Count",
        "value": "245.0 thou/mm3",
        "reference_range": "150.00 - 450.00 thou/mm3",
        "status": "normal",
        "significance": null
      }
    ],
    "abnormalities": [
      {
        "parameter_name": "Hemoglobin",
        "description": "low at 12.00 g/dL, below the normal range of 13.00 - 17.00 g/dL, indicating mild anemia.",
        "observed_value": "12.00 g/dL",
        "estimated_severity": "mild",
        "recommendation": "Consult healthcare provider for detailed evaluation."
      },
      {
        "parameter_name": "Packed Cell Volume (PCV)",
        "description": "slightly low at 37.70%, suggesting reduced red blood cell volume.",
        "observed_value": "37.70%",
        "estimated_severity": "mild",
        "recommendation": "Consult healthcare provider for detailed evaluation."
      },
      {
        "parameter_name": "RBC Count",
        "description": "slightly elevated at 5.79 mill/mm3, above the upper limit of 5.50 mill/mm3.",
        "observed_value": "5.79 mill/mm3",
        "estimated_severity": "mild",
        "recommendation": "Consult healthcare provider for detailed evaluation."
      },
      {
        "parameter_name": "MCV (mean corpuscular volume)",
        "description": "significantly low at 65.00 fL, indicating microcytic red blood cells, often seen in iron deficiency anemia or thalassemia.",
        "observed_value": "65.00 fL",
        "estimated_severity": "severe",
        "recommendation": "Consult healthcare provider for detailed evaluation."
      },
      {
        "parameter_name": "MCH (mean corpuscular hemoglobin)",
        "description": "low at 20.70 pg, indicating less hemoglobin per red blood cell.",
        "observed_value": "20.70 pg",
        "estimated_severity": "unknown",
        "recommendation": "Consult healthcare provider for detailed evaluation."
      },
      {
        "parameter_name": "MCHC (mean corpuscular hemoglobin concentration)",
        "description": "slightly low at 31.90 g/dL.",
        "observed_value": "31.90 g/dL",
        "estimated_severity": "mild",
        "recommendation": "Consult healthcare provider for detailed evaluation."
      },
      {
        "parameter_name": "RDW (red cell distribution width)",
        "description": "elevated at 15.90%, indicating variation in red blood cell size, which supports anisocytosis often seen in anemia.",
        "observed_value": "15.90%",
        "estimated_severity": "unknown",
        "recommendation": "Consult healthcare provider for detailed evaluation."
      },
      {
        "parameter_name": "Segmented neutrophils percentage",
        "description": "slightly low at 39.60%, and absolute neutrophil count is low at 1.66 thou/mm3, which may suggest mild neutropenia or a shift in white cell distribution.",
        "observed_value": "39.60%",
        "estimated_severity": "mild",
        "recommendation": "Consult healthcare provider for detailed evaluation."
      },
      {
        "parameter_name": "Lymphocytes percentage",
        "description": "high at 50.30%, though absolute lymphocyte count is normal, which may indicate a reactive or viral process.",
        "observed_value": "50.30%",
        "estimated_severity": "unknown",
        "recommendation": "Consult healthcare provider for detailed evaluation."
      }
    ],
    "recommendations": [
      "Further evaluation for anemia is recommended, including iron studies (serum ferritin, serum iron, TIBC) to confirm iron deficiency or other causes.",
      "Monitor white blood cell counts and consider clinical correlation for possible infections or immune conditions due to neutropenia and lymphocytosis.",
      "Follow-up CBC after treatment or clinical intervention to assess response and progression."
    ],
    "follow_up": "Consult with healthcare provider for further guidance.",
    "other_details": [
      "Unmatched in IDENTIFIED_PARAMETERS: Differential Leukocyte Count (DLC):",
      "Unmatched in IDENTIFIED_PARAMETERS: Absolute Leukocyte Count:",
      "Unmatched in IDENTIFIED_PARAMETERS: ---",
      "Unparsed short line in OBSERVED_ABNORMALITIES: --"
    ]
  },
  "follow_up_recommendations": "Consult with healthcare provider for further guidance."
}